depglance/__init__.py
depglance/__main__.py
depglance/cli.py
depglance/exporter.py
depglance/graph.py
depglance/parser.py
depglance/scanner.py
depglance/server.py
depglance-0.1.8.dist-info/licenses/LICENSE
tests/__init__.py
tests/test_graph.py
tests/test_parser.py
tests/test_scanner.py
depglance-0.1.8.dist-info/METADATA
depglance-0.1.8.dist-info/WHEEL
depglance-0.1.8.dist-info/entry_points.txt
depglance-0.1.8.dist-info/top_level.txt
depglance-0.1.8.dist-info/RECORD
