Metadata-Version: 2.4
Name: depglance
Version: 0.1.8
Summary: Python Dependency Visualizer with Vulnerability Insights
Home-page: https://github.com/devprajeet/depglance
Author: Prajeet Singh
Author-email: Prajeet Singh <dev.prajeet2016@gmail.com>
License: MIT
Project-URL: Homepage, https://github.com/devprajeet/depglance
Project-URL: Source, https://github.com/devprajeet/depglance
Project-URL: Tracker, https://github.com/devprajeet/depglance/issues
Requires-Python: >=3.7
License-File: LICENSE
Requires-Dist: requests
Requires-Dist: pyvis
Requires-Dist: toml
Dynamic: author
Dynamic: home-page
Dynamic: license-file
Dynamic: requires-python
